gtasks_cli/__init__.py
gtasks_cli/__main__.py
gtasks_cli/main.py
gtasks_cli/mcp_server.py
gtasks_cli/setup_assistant.py
gtasks_cli/ai/client.py
gtasks_cli/ai/tools.py
gtasks_cli/analytics/__init__.py
gtasks_cli/cli/__init__.py
gtasks_cli/commands/__init__.py
gtasks_cli/commands/account.py
gtasks_cli/commands/add.py
gtasks_cli/commands/advanced_sync.py
gtasks_cli/commands/ai.py
gtasks_cli/commands/auth.py
gtasks_cli/commands/config.py
gtasks_cli/commands/deduplicate.py
gtasks_cli/commands/delete.py
gtasks_cli/commands/done.py
gtasks_cli/commands/generate_report.py
gtasks_cli/commands/interactive.py
gtasks_cli/commands/interactive_help.py
gtasks_cli/commands/list.py
gtasks_cli/commands/mcp.py
gtasks_cli/commands/search.py
gtasks_cli/commands/summary.py
gtasks_cli/commands/tasklist.py
gtasks_cli/commands/update.py
gtasks_cli/commands/view.py
gtasks_cli/commands/interactive_utils/__init__.py
gtasks_cli/commands/interactive_utils/add_commands.py
gtasks_cli/commands/interactive_utils/bulk_update_commands.py
gtasks_cli/commands/interactive_utils/common.py
gtasks_cli/commands/interactive_utils/delete_commands.py
gtasks_cli/commands/interactive_utils/display.py
gtasks_cli/commands/interactive_utils/done_commands.py
gtasks_cli/commands/interactive_utils/editor.py
gtasks_cli/commands/interactive_utils/initial_commands.py
gtasks_cli/commands/interactive_utils/list_commands.py
gtasks_cli/commands/interactive_utils/piped_commands.py
gtasks_cli/commands/interactive_utils/search.py
gtasks_cli/commands/interactive_utils/tag_commands.py
gtasks_cli/commands/interactive_utils/task_details.py
gtasks_cli/commands/interactive_utils/undo_manager.py
gtasks_cli/commands/interactive_utils/update_commands.py
gtasks_cli/commands/interactive_utils/update_tags_commands.py
gtasks_cli/core/__init__.py
gtasks_cli/core/task_manager.py
gtasks_cli/integrations/__init__.py
gtasks_cli/integrations/advanced_sync_manager.py
gtasks_cli/integrations/advanced_sync_manager.py.orig
gtasks_cli-0.1.6.dist-info/METADATA
gtasks_cli-0.1.6.dist-info/WHEEL
gtasks_cli-0.1.6.dist-info/entry_points.txt
gtasks_cli-0.1.6.dist-info/licenses/LICENSE
gtasks_cli-0.1.6.dist-info/RECORD
