Metadata-Version: 2.4
Name: gtasks-cli
Version: 0.1.6
Summary: A powerful command-line interface for managing Google Tasks with enhanced features and functionality which is secure and easy to use with advanced features.
Project-URL: Homepage, https://github.com/sirusdas/gtasks-terminal
Project-URL: Bug Reports, https://github.com/sirusdas/gtasks-terminal/issues
Project-URL: Source, https://github.com/sirusdas/gtasks-terminal
License: MIT
License-File: LICENSE
Classifier: Development Status :: 4 - Beta
Classifier: Intended Audience :: Developers
Classifier: Intended Audience :: End Users/Desktop
Classifier: License :: OSI Approved :: MIT License
Classifier: Operating System :: OS Independent
Classifier: Programming Language :: Python :: 3
Classifier: Programming Language :: Python :: 3.7
Classifier: Programming Language :: Python :: 3.8
Classifier: Programming Language :: Python :: 3.9
Classifier: Programming Language :: Python :: 3.10
Classifier: Programming Language :: Python :: 3.11
Classifier: Topic :: Software Development :: Libraries :: Python Modules
Classifier: Topic :: Utilities
Requires-Python: >=3.7
Requires-Dist: appdirs>=1.4.4
Requires-Dist: click>=8.1.0
Requires-Dist: colorama>=0.4.6
Requires-Dist: cryptography>=41.0.0
Requires-Dist: google-api-python-client>=2.0
Requires-Dist: google-auth-oauthlib>=1.0.0
Requires-Dist: litellm>=1.42.0
Requires-Dist: matplotlib>=3.7.0
Requires-Dist: mcp>=1.0.0
Requires-Dist: prompt-toolkit>=3.0.0
Requires-Dist: pydantic>=2.0.0
Requires-Dist: python-dateutil>=2.8.0
Requires-Dist: pytz>=2023.3
Requires-Dist: pyyaml>=6.0
Requires-Dist: requests>=2.31.0
Requires-Dist: rich>=13.0.0
Requires-Dist: sqlalchemy>=2.0.0
Requires-Dist: tabulate>=0.9.0
Provides-Extra: dev
Requires-Dist: black; extra == 'dev'
Requires-Dist: build; extra == 'dev'
Requires-Dist: flake8; extra == 'dev'
Requires-Dist: pytest>=6.0; extra == 'dev'
Requires-Dist: twine; extra == 'dev'
